process_tree_widget/__init__.py
process_tree_widget/tree.py
process_tree_widget/utils.py
process_tree_widget/static/widget.js
process_tree_widget-0.0.1.dist-info/METADATA
process_tree_widget-0.0.1.dist-info/WHEEL
process_tree_widget-0.0.1.dist-info/RECORD
