Metadata-Version: 2.4
Name: process_tree_widget
Version: 0.0.1
Requires-Dist: anywidget
Requires-Dist: ibis-framework
Requires-Dist: pydantic
Requires-Dist: treelib
